{
    "image": "\/app\/images\/no_image.png",
    "name": "Hanzen",
    "location": "Ca-elum",
    "appearance": "Jest najs\u0142abszy z grupy \u0142owc\u00f3w nagr\u00f3d z Iceberg, jako jedyny nie jest magiem. Ma bia\u0142e postrz\u0119pione ku g\u00f3rze niczym Lyon (ten kolega Graya) w\u0142osy. Nosi ciemny mundur z obrysem w kolorze srebra. Nie lubi walki, brzydzi si\u0119 przemoc\u0105. Jest nieco wym\u0105drza\u0142y, ale za to bardzo inteligentny i jak przysta\u0142o na tego typu postaci, nosi okulary. 72kg, 183cm, ok. 27 lat.",
    "strength": "15",
    "endurance": "45",
    "speed": "70",
    "reaction": "110",
    "magic_energy_control": "",
    "concentration": "",
    "magic": ""
}